bentomlx-0.0.2.dist-info/METADATA
bentomlx-0.0.2.dist-info/WHEEL
bentomlx-0.0.2.dist-info/licenses/LICENSE
bentomlx/__init__.py
bentomlx/featurestore/__init__.py
bentomlx/featurestore/backend/__init__.py
bentomlx/featurestore/backend/aerospike_backend/__init__.py
bentomlx/featurestore/backend/aerospike_backend/repository.py
bentomlx/featurestore/backend/redis_backend/__init__.py
bentomlx/featurestore/backend/redis_backend/repository.py
bentomlx/featurestore/backend/repository.py
bentomlx/featurestore/festurestore.py
bentomlx/featurestore/settings.py
bentomlx/intel/__init__.py
bentomlx/intel/custom_ops/__init__.py
bentomlx/intel/custom_ops/_core/CMakeLists.txt
bentomlx/intel/custom_ops/_core/bert_layer/CMakeLists.txt
bentomlx/intel/custom_ops/_core/bert_layer/bert_context.h
bentomlx/intel/custom_ops/_core/bert_layer/bert_layer_quant_int8.h
bentomlx/intel/custom_ops/_core/bert_layer/bert_profiler.hpp
bentomlx/intel/custom_ops/_core/bert_layer/bert_type_traits.h
bentomlx/intel/custom_ops/_core/bert_layer/dnnl_attr.hpp
bentomlx/intel/custom_ops/_core/bert_layer/dnnl_common.h
bentomlx/intel/custom_ops/_core/bert_layer/dnnl_data.hpp
bentomlx/intel/custom_ops/_core/bert_layer/dnnl_ops.hpp
bentomlx/intel/custom_ops/_core/bert_layer/quant_factors.hpp
bentomlx/intel/custom_ops/_core/pytorch_op/CMakeLists.txt
bentomlx/intel/custom_ops/_core/pytorch_op/bert_op.cpp
bentomlx/intel/custom_ops/_core/pytorch_op/bert_op.hpp
bentomlx/intel/custom_ops/_core/pytorch_op/libBertOpPT.so
bentomlx/intel/custom_ops/bert_op/__init__.py
bentomlx/intel/custom_ops/bert_op/torch/__init__.py
bentomlx/intel/custom_ops/bert_op/torch/bert_op_torch.py
bentomlx/intel/ipex/__init__.py
bentomlx-0.0.2.dist-info/RECORD
