Metadata-Version: 2.1
Name: bentomlx
Version: 0.0.2
Author-Email: kimsoungryoul <kimsoungryoul@gmail.com>
License: Apache-2.0
Requires-Python: >=3.10
Requires-Dist: bentoml>=1.1.10
Requires-Dist: pydantic-settings>=1.10.0
Requires-Dist: async-lru>=2.0.4
Requires-Dist: torch<=1.13.1; extra == "ipex"
Requires-Dist: intel-extension-for-pytorch>=1.13.1; extra == "ipex"
Requires-Dist: aerospike>=11.0.0; extra == "aerospike"
Requires-Dist: redis[hiredis]>=4.6.0; extra == "redis"
Provides-Extra: ipex
Provides-Extra: aerospike
Provides-Extra: redis
